{
  "method": "page_sources",
  "sources_found": [
    {
      "count": 606,
      "exists": true,
      "name": "regTrainsSource"
    },
    {
      "count": 103,
      "exists": true,
      "name": "unregTrainsSource"
    },
    {
      "count": 651,
      "exists": true,
      "name": "markerSource"
    },
    {
      "count": 709,
      "exists": true,
      "name": "arrowMarkersSource"
    },
    {
      "count": 0,
      "exists": false,
      "name": "trainSource"
    },
    {
      "count": 0,
      "exists": false,
      "name": "trainMarkers"
    }
  ],
  "raw_count": 1744,
  "au_count": 1639,
  "url_after_open": "https://trainfinder.otenko.com/home/nextlevel",
  "hasMap": true,
  "hasOl": true,
  "sample": {
    "id": "9305",
    "train_number": "NB928",
    "train_name": "9305",
    "loco": "",
    "operator": "",
    "origin": "Narrabri",
    "destination": "NCIG Kooragang",
    "speed": 56,
    "heading": 0,
    "km": "199 km",
    "time": "10:21:00",
    "date": "03/04/2026",
    "description": "PN Coal",
    "cId": "18402348-3c0f-4dee-8bf5-3a8bbbf9945b",
    "servId": "e8ede4f9-c6ac-4b0f-9cbc-7f5f67e3c2a1",
    "trKey": "9305",
    "lat": -32.719667,
    "lon": 151.48688
  }
}