{
  "method": "page_sources",
  "sources_found": [
    {
      "count": 537,
      "exists": true,
      "name": "regTrainsSource"
    },
    {
      "count": 87,
      "exists": true,
      "name": "unregTrainsSource"
    },
    {
      "count": 587,
      "exists": true,
      "name": "markerSource"
    },
    {
      "count": 624,
      "exists": true,
      "name": "arrowMarkersSource"
    },
    {
      "count": 0,
      "exists": false,
      "name": "trainSource"
    },
    {
      "count": 0,
      "exists": false,
      "name": "trainMarkers"
    }
  ],
  "raw_count": 1542,
  "au_count": 1481,
  "url_after_open": "https://trainfinder.otenko.com/home/nextlevel",
  "hasMap": true,
  "hasOl": true,
  "sample": {
    "id": "QLD7DBC12428F13E6FACD8FDFD0866122D3_DY39",
    "train_number": "DY39",
    "train_name": "QLD7DBC12428F13E6FACD8FDFD0866122D3_DY39",
    "loco": "",
    "operator": "",
    "origin": "Springfield",
    "destination": "Redcliffe Peninsula",
    "speed": 0,
    "heading": 0,
    "km": "",
    "time": "15:44:03",
    "date": "18/04/2026",
    "description": "SPRP",
    "cId": "c077596c-452c-48f8-8e11-7d925e1f0146",
    "servId": "",
    "trKey": "QLD7DBC12428F13E6FACD8FDFD0866122D3_DY39",
    "lat": -27.225809,
    "lon": 153.080154
  }
}