{
  "method": "page_sources",
  "sources_found": [
    {
      "count": 774,
      "exists": true,
      "name": "regTrainsSource"
    },
    {
      "count": 75,
      "exists": true,
      "name": "unregTrainsSource"
    },
    {
      "count": 999,
      "exists": true,
      "name": "markerSource"
    },
    {
      "count": 849,
      "exists": true,
      "name": "arrowMarkersSource"
    },
    {
      "count": 0,
      "exists": false,
      "name": "trainSource"
    },
    {
      "count": 0,
      "exists": false,
      "name": "trainMarkers"
    }
  ],
  "raw_count": 2198,
  "au_count": 2101,
  "url_after_open": "https://trainfinder.otenko.com/home/nextlevel",
  "hasMap": true,
  "hasOl": true,
  "sample": {
    "id": "ACD6066",
    "train_number": "1PM1",
    "train_name": "ACD6066",
    "loco": "",
    "operator": "",
    "origin": "Aurizon, Forrestfield",
    "destination": "North Dynon",
    "speed": 0,
    "heading": 0,
    "km": "93 km",
    "time": "19:20:00",
    "date": "14/04/2026",
    "description": "Aurizon Intermodal",
    "cId": "01e5aad9-fc0c-4b7a-a39d-d5166bf44f25",
    "servId": "210af4fb-3054-4d8c-a39f-a1d6851bbc20",
    "trKey": "ACD6066",
    "lat": -32.483043,
    "lon": 137.770667
  }
}