{
  "method": "page_sources",
  "sources_found": [
    {
      "count": 170,
      "exists": true,
      "name": "regTrainsSource"
    },
    {
      "count": 71,
      "exists": true,
      "name": "unregTrainsSource"
    },
    {
      "count": 357,
      "exists": true,
      "name": "markerSource"
    },
    {
      "count": 241,
      "exists": true,
      "name": "arrowMarkersSource"
    },
    {
      "count": 0,
      "exists": false,
      "name": "trainSource"
    },
    {
      "count": 0,
      "exists": false,
      "name": "trainMarkers"
    }
  ],
  "raw_count": 661,
  "au_count": 633,
  "url_after_open": "https://trainfinder.otenko.com/home/nextlevel",
  "hasMap": true,
  "hasOl": true,
  "sample": {
    "id": "MM-978M",
    "train_number": "LIL",
    "train_name": "MM-978M",
    "loco": "",
    "operator": "",
    "origin": "",
    "destination": "",
    "speed": 0,
    "heading": 0,
    "km": "",
    "time": "04:54:57",
    "date": "19/04/2026",
    "description": "Lilydale Line",
    "cId": "8a12cdda-ab2e-43ce-baad-e3f00fe7fa9c",
    "servId": "d0734149-e192-4adb-a9d4-69611ec9097b",
    "trKey": "MM-978M",
    "lat": -37.821831,
    "lon": 145.039337
  }
}