{
  "method": "page_sources",
  "sources_found": [
    {
      "count": 41,
      "exists": true,
      "name": "regTrainsSource"
    },
    {
      "count": 48,
      "exists": true,
      "name": "unregTrainsSource"
    },
    {
      "count": 1,
      "exists": true,
      "name": "markerSource"
    },
    {
      "count": 89,
      "exists": true,
      "name": "arrowMarkersSource"
    },
    {
      "count": 0,
      "exists": false,
      "name": "trainSource"
    },
    {
      "count": 0,
      "exists": false,
      "name": "trainMarkers"
    }
  ],
  "raw_count": 179,
  "au_count": 166,
  "url_after_open": "https://trainfinder.otenko.com/home/nextlevel",
  "hasMap": true,
  "hasOl": true,
  "sample": {
    "id": "SO3",
    "train_number": "985T",
    "train_name": "SO3",
    "loco": "",
    "operator": "",
    "origin": "longreach",
    "destination": "brisbane-roma-st",
    "speed": 0,
    "heading": 0,
    "km": "",
    "time": "03:27:19",
    "date": "24/04/2026",
    "description": "Spirit of the Outback",
    "cId": "8fa70797-777c-41e6-8be8-8bd7cd38b666",
    "servId": "",
    "trKey": "SO3",
    "lat": -23.862907,
    "lon": 151.23693
  }
}