[
  {
    "generated": "2026-04-29T20:07:54.281919Z",
    "source_trains": 764,
    "seen_this_run": 185,
    "existing_before": 283,
    "new_added": 0,
    "final_count": 283,
    "new_loco_numbers": []
  },
  {
    "generated": "2026-04-29T18:54:54.317368Z",
    "source_trains": 764,
    "seen_this_run": 185,
    "existing_before": 283,
    "new_added": 0,
    "final_count": 283,
    "new_loco_numbers": []
  },
  {
    "generated": "2026-04-29T18:28:19.914186Z",
    "source_trains": 764,
    "seen_this_run": 185,
    "existing_before": 267,
    "new_added": 16,
    "final_count": 283,
    "new_loco_numbers": [
      "MM864M",
      "MM14M",
      "VLINE8702",
      "MM9931M",
      "MM9952M",
      "VLINE8102",
      "MM246M",
      "4829",
      "RL301",
      "8115",
      "HM2703",
      "8158",
      "VLINE8400",
      "MM212M",
      "MM880M",
      "LE2855"
    ]
  },
  {
    "generated": "2026-04-29T18:02:14.191278Z",
    "source_trains": 648,
    "seen_this_run": 174,
    "existing_before": 249,
    "new_added": 18,
    "final_count": 267,
    "new_loco_numbers": [
      "MM9938M",
      "MM9963M",
      "MM9961M",
      "MM9936M",
      "LE2851",
      "TE2813",
      "MM972M",
      "MM768M",
      "BL26",
      "TT05",
      "HM2753",
      "HM2706",
      "TE2808",
      "8203",
      "TE2807",
      "1435",
      "GWB102",
      "GWU013"
    ]
  },
  {
    "generated": "2026-04-29T17:31:31.313959Z",
    "source_trains": 562,
    "seen_this_run": 171,
    "existing_before": 212,
    "new_added": 37,
    "final_count": 249,
    "new_loco_numbers": [
      "HM2756",
      "5032",
      "HM2705",
      "HM2755",
      "DS003",
      "RB2353",
      "8206",
      "9307",
      "QL007",
      "TT08",
      "8249",
      "5031",
      "XRN005",
      "TT02",
      "XRN029",
      "LDP004",
      "5009",
      "CF4429",
      "LZ3114",
      "GWB104",
      "ACB4403",
      "ACD6049",
      "TE2805",
      "TE2803",
      "TT105",
      "QBX003",
      "1437",
      "6003",
      "44202",
      "44204",
      "QBX004",
      "8135",
      "G533",
      "CSR023",
      "G536",
      "BL33",
      "MM9927M"
    ]
  },
  {
    "generated": "2026-04-29T17:19:50.669172Z",
    "source_trains": 813,
    "seen_this_run": 212,
    "existing_before": 0,
    "new_added": 212,
    "final_count": 212,
    "new_loco_numbers": [
      "G516",
      "1428",
      "PHC001",
      "8169",
      "NR11",
      "8207",
      "C502",
      "G534",
      "CEY007",
      "PKLA4",
      "8030",
      "6002",
      "6001",
      "5030",
      "TJ096",
      "TT103",
      "5034",
      "G513",
      "8225",
      "MAN013",
      "8202",
      "1102",
      "MAN007",
      "NR6",
      "TT117",
      "TT03",
      "6011",
      "6027",
      "8217",
      "8215",
      "CLP13",
      "SSR103",
      "XP2006",
      "XP2011",
      "8210",
      "MAN017",
      "QE002",
      "NR20",
      "MAN004",
      "NR65",
      "NR64",
      "6025",
      "QR5404",
      "EA2503",
      "G514",
      "RA2303",
      "TT202",
      "TT123",
      "9029",
      "XRN021",
      "9203",
      "GWU008",
      "CF4405",
      "CF4410",
      "CEY006",
      "CEY004",
      "VLINE8457",
      "GL111",
      "6029",
      "NR94",
      "NR93",
      "NR102",
      "CSR021",
      "VL57",
      "MM834M",
      "MM522M",
      "MM838M",
      "CLP12",
      "MM624M",
      "MM158M",
      "VLINE8058",
      "VL22",
      "8114",
      "VLINE8164",
      "NR95",
      "MM718M",
      "MM76M",
      "MM946M",
      "MM934M",
      "MM914M",
      "MM962M",
      "MM982M",
      "MM280M",
      "MM928M",
      "MM260M",
      "MM82M",
      "MM232M",
      "MM172M",
      "MM502M",
      "MM810M",
      "MM152M",
      "MM9970M",
      "VLINE8459",
      "MM9966M",
      "NR5",
      "6008",
      "TT126",
      "XRN018",
      "9301",
      "6021",
      "LDP008",
      "8161",
      "CF4425",
      "QE003",
      "QL019",
      "NR35",
      "QL009",
      "QR5400",
      "LDP002",
      "TT206",
      "6028",
      "5041",
      "TT107",
      "HM2701",
      "XP2001",
      "ACD6058",
      "CSR020",
      "NR112",
      "NR13",
      "XP2005",
      "XRN017",
      "TT130",
      "TT115",
      "HM2702",
      "TT110",
      "8239",
      "5011",
      "XRN009",
      "5025",
      "5021",
      "9313",
      "9305",
      "M437",
      "CF4421",
      "MRL001",
      "T373",
      "MAN015",
      "XRN028",
      "CF4427",
      "5042",
      "CF4401",
      "TT129",
      "SSR102",
      "LE2853",
      "C509",
      "M865",
      "FIE001",
      "8223",
      "8209",
      "9302",
      "9312",
      "8240",
      "9311",
      "CF4424",
      "XRN022",
      "9025",
      "NR75",
      "SCT009",
      "NR37",
      "GWB103",
      "GWA008",
      "ACD6065",
      "MM674M",
      "CSR010",
      "ACD6059",
      "MM9965M",
      "GL105",
      "GWA002",
      "ACD6056",
      "SCT001",
      "NR10",
      "ACD6074",
      "ACD6057",
      "NR4",
      "CSR015",
      "Q4004",
      "Q4012",
      "Q4016",
      "Q4013",
      "ACD6052",
      "CSR019",
      "NR115",
      "VLINE8819",
      "MM830M",
      "ACD6047",
      "MM9946M",
      "MM9924M",
      "MM9914M",
      "VLINE8161",
      "VLINE8059",
      "9408",
      "9406",
      "VLINE8163",
      "VLINE8061",
      "9410",
      "GWU014",
      "ACD6069",
      "GWA009",
      "GL103",
      "SCT008",
      "NR47",
      "NR109",
      "GWA004",
      "ACD6071",
      "ACD6066",
      "NR97",
      "NR113",
      "NR14",
      "ACB4404",
      "NR107",
      "NR78",
      "NR46"
    ]
  }
]